{"stats":{"minecraft:mined":{"biomesoplenty:red_maple_leaves":1},"minecraft:killed":{"minecraft:skeleton":1},"minecraft:picked_up":{"minecraft:torch":17,"minecraft:redstone_torch":2,"minecraft:soul_torch":1},"minecraft:used":{"minecraft:redstone_torch":1,"minecraft:torch":15,"minecraft:diamond_sword":1,"minecraft:flint_and_steel":2,"minecraft:cod":1,"minecraft:soul_torch":1},"minecraft:dropped":{"minecraft:redstone_torch":2,"minecraft:soul_torch":1,"minecraft:torch":17},"minecraft:custom":{"minecraft:time_since_rest":362588,"minecraft:crouch_one_cm":5470,"minecraft:play_time":362588,"minecraft:sprint_one_cm":140255,"minecraft:walk_one_cm":75789,"minecraft:sneak_time":4322,"minecraft:mob_kills":1,"minecraft:drop":20,"minecraft:jump":651,"minecraft:damage_dealt":70,"minecraft:leave_game":12,"minecraft:time_since_death":362588,"minecraft:total_world_time":362588,"minecraft:fly_one_cm":410144}},"DataVersion":4189}